MANIFEST.in
README.md
setup.py
wireless_radar.egg-info/PKG-INFO
wireless_radar.egg-info/SOURCES.txt
wireless_radar.egg-info/dependency_links.txt
wireless_radar.egg-info/entry_points.txt
wireless_radar.egg-info/requires.txt
wireless_radar.egg-info/top_level.txt
wirelessradar/__init__.py
wirelessradar/bprox.py
wirelessradar/launcher.py
wirelessradar/mrssi.py
wirelessradar/rfdiff.py
wirelessradar/wprox.py
wirelessradar/wscan.py