Metadata-Version: 1.1
Name: wireless-radar
Version: 0.2.3
Summary: various tools to map the wireless environment
Home-page: https://github.com/stef/wireless-radar
Author: Stefan Marsiske
Author-email: s@ctrlc.hu
License: AGPLv3
Keywords: 802.11 wireless wifi scanning direction-finding
Platform: UNKNOWN
Classifier: Development Status :: 4 - Beta
Classifier: License :: OSI Approved :: GNU Affero General Public License v3 or later (AGPLv3+)
